avget/__init__.py
avget/__main__.py
avget/__version__.py
tests/__init__.py
tests/test_main.py
AVGet-0.0.1.dist-info/LICENSE
AVGet-0.0.1.dist-info/METADATA
AVGet-0.0.1.dist-info/WHEEL
AVGet-0.0.1.dist-info/entry_points.txt
AVGet-0.0.1.dist-info/top_level.txt
AVGet-0.0.1.dist-info/RECORD
